{
    "version": "1.0",
    "iterationId": "iter-5",
    "storyId": "Story-5.0",
    "moduleId": "dashboard",
    "status": "Partial",
    "completedItems": [
        "Item 1: 後端 API 擴展 - toolService.ts, fileService.ts, routes.ts 擴展"
    ],
    "pendingItems": [
        "Item 2: 前端 HTML 重構",
        "Item 3: 前端 JS 模組化"
    ],
    "technicalHighlights": [
        "新增 8 個後端 API endpoints 支援工具執行和檔案瀏覽",
        "toolService 封裝所有工具執行邏輯，統一錯誤處理",
        "fileService 提供檔案樹和門控結果查詢",
        "完整單元測試覆蓋，21 個新測試",
        "GEMS Gate 100% 通過，P0/P1 Coverage 100%"
    ],
    "technicalDebt": [],
    "testResults": {
        "total": 218,
        "passed": 218,
        "failed": 0,
        "newTests": 21
    },
    "gemsGate": {
        "passed": true,
        "functions": 43,
        "byPriority": {
            "P0": 8,
            "P1": 14,
            "P2": 14,
            "P3": 7
        },
        "coverage": 100
    },
    "nextIteration": {
        "suggestedGoal": "完成 Story-5.0 剩餘 Items 並繼續 Story-5.1",
        "suggestedItems": [
            "Story-5.0 Item 2: 前端 HTML 重構（側邊欄、頁籤容器）",
            "Story-5.0 Item 3: 前端 JS 模組化（api.js, navigation.js, toast.js）",
            "Story-5.1: 工具操作面板 UI（init-project, scaffold 表單）",
            "Story-5.2: 檔案瀏覽器（樹狀結構顯示）"
        ]
    },
    "files": {
        "created": [
            "src/modules/dashboard/services/toolService.ts",
            "src/modules/dashboard/services/fileService.ts",
            "src/modules/dashboard/__tests__/toolService.test.ts",
            "src/modules/dashboard/__tests__/fileService.test.ts",
            "iterations/iter-5/requirement_spec_iter-5.md",
            "iterations/iter-5/implementation_plan_Story-5.0.md"
        ],
        "modified": [
            "src/modules/dashboard/api/routes.ts"
        ]
    }
}